odoo/addons/barcodes_generator_product/README.rst
odoo/addons/barcodes_generator_product/__init__.py
odoo/addons/barcodes_generator_product/__manifest__.py
odoo/addons/barcodes_generator_product/demo/barcode_rule.xml
odoo/addons/barcodes_generator_product/demo/function.xml
odoo/addons/barcodes_generator_product/demo/product.xml
odoo/addons/barcodes_generator_product/demo/res_users.xml
odoo/addons/barcodes_generator_product/i18n/barcodes_generator_product.pot
odoo/addons/barcodes_generator_product/i18n/es_ES.po
odoo/addons/barcodes_generator_product/i18n/fr.po
odoo/addons/barcodes_generator_product/i18n/hr.po
odoo/addons/barcodes_generator_product/i18n/it.po
odoo/addons/barcodes_generator_product/i18n/nl_NL.po
odoo/addons/barcodes_generator_product/i18n/zh_CN.po
odoo/addons/barcodes_generator_product/models/__init__.py
odoo/addons/barcodes_generator_product/models/barcode_rule.py
odoo/addons/barcodes_generator_product/models/product_product.py
odoo/addons/barcodes_generator_product/models/product_template.py
odoo/addons/barcodes_generator_product/readme/CONFIGURE.rst
odoo/addons/barcodes_generator_product/readme/CONTRIBUTORS.rst
odoo/addons/barcodes_generator_product/readme/CREDITS.rst
odoo/addons/barcodes_generator_product/readme/DESCRIPTION.rst
odoo/addons/barcodes_generator_product/readme/USAGE.rst
odoo/addons/barcodes_generator_product/static/description/icon.png
odoo/addons/barcodes_generator_product/static/description/index.html
odoo/addons/barcodes_generator_product/static/description/product_template_manual_generation.png
odoo/addons/barcodes_generator_product/tests/__init__.py
odoo/addons/barcodes_generator_product/tests/test_barcodes_generator_product.py
odoo/addons/barcodes_generator_product/views/view_product_product.xml
odoo/addons/barcodes_generator_product/views/view_product_template.xml
odoo13_addon_barcodes_generator_product-13.0.1.0.1.dev7.dist-info/METADATA
odoo13_addon_barcodes_generator_product-13.0.1.0.1.dev7.dist-info/WHEEL
odoo13_addon_barcodes_generator_product-13.0.1.0.1.dev7.dist-info/top_level.txt
odoo13_addon_barcodes_generator_product-13.0.1.0.1.dev7.dist-info/RECORD
